MANIFEST.in
README.md
setup.py
homekeeper/__init__.py
homekeeper/__main__.py
homekeeper/levels.py
homekeeper/sound.py
homekeeper/fonts/BalooThambi-Regular.ttf
homekeeper/fonts/OFL.txt
homekeeper/fonts/__init__.py
homekeeper/images/README.md
homekeeper/images/__init__.py
homekeeper/images/black_dirty.png
homekeeper/images/blue_dirty.png
homekeeper/images/broom_0.png
homekeeper/images/broom_0.xcf
homekeeper/images/cyan_dirty.png
homekeeper/images/dirty_0.xcf
homekeeper/images/licenses.txt
homekeeper/images/purple_dirty.png
homekeeper/images/red_dirty.png
homekeeper/images/yellow_dirty.png
homekeeper/maps/__init__.py
homekeeper/maps/bedroom.txt
homekeeper/maps/bedroom_small.txt
homekeeper/maps/bedroom_small_with_bed.txt
homekeeper_game.egg-info/PKG-INFO
homekeeper_game.egg-info/SOURCES.txt
homekeeper_game.egg-info/dependency_links.txt
homekeeper_game.egg-info/requires.txt
homekeeper_game.egg-info/top_level.txt